LICENSE
README.md
setup.cfg
setup.py
analogistics/__init__.py
analogistics/clean.py
analogistics/explore.py
analogistics/reduce.py
analogistics/transform.py
analogistics.egg-info/PKG-INFO
analogistics.egg-info/SOURCES.txt
analogistics.egg-info/dependency_links.txt
analogistics.egg-info/requires.txt
analogistics.egg-info/top_level.txt
analogistics/chart/__init__.py
analogistics/chart/chart_3D_surface.py
analogistics/chart/chart_map.py
analogistics/data/__init__.py
analogistics/data/data_generator_distribution.py
analogistics/data/data_generator_warehouse.py
analogistics/graph/__init__.py
analogistics/graph/graph.py
analogistics/learning/__init__.py
analogistics/learning/analogizers_grids.py
analogistics/learning/bayesians_grids.py
analogistics/learning/connectionists_grids.py
analogistics/learning/ensemble_grids.py
analogistics/learning/evaluate.py
analogistics/learning/grids.py
analogistics/learning/linear_grids.py
analogistics/learning/symbolists_grids.py
analogistics/learning/unsupervised_models.py
analogistics/statistics/__init__.py
analogistics/statistics/sample.py
analogistics/statistics/time_series.py
analogistics/supply_chain/__init__.py
analogistics/supply_chain/information_framework.py
analogistics/supply_chain/P1_family_problem/__init__.py
analogistics/supply_chain/P1_family_problem/part_classification.py
analogistics/supply_chain/P2_assignment_problem/__init__.py
analogistics/supply_chain/P2_assignment_problem/warehousing_ABC_saving.py
analogistics/supply_chain/P3_flow_problem/__init__.py
analogistics/supply_chain/P3_flow_problem/assessFlows.py
analogistics/supply_chain/P5_power_problem/__init__.py
analogistics/supply_chain/P5_power_problem/setWarehouseInventory.py
analogistics/supply_chain/P5_power_problem/warehouseAllocation.py
analogistics/supply_chain/P6_placement_problem/__init__.py
analogistics/supply_chain/P6_placement_problem/distribution_geocoder.py
analogistics/supply_chain/P6_placement_problem/distribution_graph_definition.py
analogistics/supply_chain/P6_placement_problem/facility_location_definition.py
analogistics/supply_chain/P6_placement_problem/locationAllocationProblem.py
