Metadata-Version: 2.1
Name: analogistics
Version: 0.2.0
Summary: Analytical Tools for Logistics System Design and Operations Management
Home-page: https://github.com/aletuf93/analogistics
Author: Alessandro Tufano
Author-email: aletuf@gmail.com
License: MIT
Download-URL: https://github.com/aletuf93/analogistics/archive/refs/tags/v0.2.0.tar.gz
Platform: UNKNOWN
Classifier: Development Status :: 1 - Planning
Classifier: Intended Audience :: Science/Research
Classifier: Programming Language :: Python :: 3.7
Requires-Python: >= 3.6
License-File: LICENSE
